{
    "pdfPath": "/assets/edge_template.pdf",
    "pageWidth": 842,
    "pageHeight": 595,
    "fields": [
        {
            "id": "centerEdgeWidth",
            "type": "number",
            "label": "Width (mm)",
            "position": {
                "x": 375,
                "y": 30,
                "width": 30,
                "height": 12
            },
            "bindsTo": "centerEdgeWidth",
            "fontSize": 10
        },
        {
            "id": "centerEdgeHeight",
            "type": "number",
            "label": "Height (mm)",
            "position": {
                "x": 45,
                "y": 105,
                "width": 30,
                "height": 12
            },
            "bindsTo": "centerEdgeHeight",
            "fontSize": 10
        },
        {
            "id": "centerEdgeHoleCount",
            "type": "number",
            "label": "Hole Count",
            "position": {
                "x": 535,
                "y": 315,
                "width": 30,
                "height": 12
            },
            "bindsTo": "centerEdgeHoleCount",
            "fontSize": 10
        },
        {
            "id": "centerEdgeHoleSize",
            "type": "number",
            "label": "Hole Size (mm)",
            "position": {
                "x": 120,
                "y": 160,
                "width": 30,
                "height": 12
            },
            "bindsTo": "centerEdgeHoleSize",
            "fontSize": 10
        },
        {
            "id": "centerEdgeHoleType",
            "type": "dropdown",
            "label": "Hole Type",
            "position": {
                "x": 45,
                "y": 165,
                "width": 40,
                "height": 12
            },
            "bindsTo": "centerEdgeHoleType",
            "fontSize": 10
        },
        {
            "id": "centerEdgePitch",
            "type": "number",
            "label": "Pitch (mm)",
            "position": {
                "x": 160,
                "y": 95,
                "width": 30,
                "height": 12
            },
            "bindsTo": "centerEdgePitch",
            "fontSize": 10
        },
        {
            "id": "centerEdgeTotalHoleDistance",
            "type": "number",
            "label": "Total Distance (mm)",
            "position": {
                "x": 350,
                "y": 50,
                "width": 30,
                "height": 12
            },
            "bindsTo": "centerEdgeTotalHoleDistance",
            "fontSize": 10
        },
        {
            "id": "centerEdgeHoleLeft",
            "type": "number",
            "label": "Hole Left (mm)",
            "position": {
                "x": 100,
                "y": 50,
                "width": 30,
                "height": 12
            },
            "bindsTo": "centerEdgeHoleLeft",
            "fontSize": 10
        },
        {
            "id": "centerEdgeHoleRight",
            "type": "number",
            "label": "Hole Right (mm)",
            "position": {
                "x": 600,
                "y": 50,
                "width": 30,
                "height": 12
            },
            "bindsTo": "centerEdgeHoleRight",
            "fontSize": 10
        }
    ]
}